[
    {
        "player": "Bruno G.",
        "team": "Newcastle",
        "team_short": "NEW",
        "goals": 5,
        "xG": 2.1,
        "overperformance": 2.9,
        "overperformance_per_90": 0.193,
        "sustainable": false,
        "form": 6.3
    },
    {
        "player": "Richarlison",
        "team": "Spurs",
        "team_short": "TOT",
        "goals": 6,
        "xG": 3.2,
        "overperformance": 2.8,
        "overperformance_per_90": 0.187,
        "sustainable": false,
        "form": 2.7
    },
    {
        "player": "Gravenberch",
        "team": "Liverpool",
        "team_short": "LIV",
        "goals": 3,
        "xG": 0.4,
        "overperformance": 2.6,
        "overperformance_per_90": 0.173,
        "sustainable": false,
        "form": 3.9
    },
    {
        "player": "Buendía",
        "team": "Aston Villa",
        "team_short": "AVL",
        "goals": 4,
        "xG": 1.6,
        "overperformance": 2.4,
        "overperformance_per_90": 0.16,
        "sustainable": false,
        "form": 2.4
    },
    {
        "player": "Caicedo",
        "team": "Chelsea",
        "team_short": "CHE",
        "goals": 3,
        "xG": 0.6,
        "overperformance": 2.4,
        "overperformance_per_90": 0.16,
        "sustainable": false,
        "form": 0.0
    },
    {
        "player": "Cash",
        "team": "Aston Villa",
        "team_short": "AVL",
        "goals": 3,
        "xG": 0.6,
        "overperformance": 2.4,
        "overperformance_per_90": 0.16,
        "sustainable": false,
        "form": 7.0
    },
    {
        "player": "Dewsbury-Hall",
        "team": "Everton",
        "team_short": "EVE",
        "goals": 4,
        "xG": 1.6,
        "overperformance": 2.4,
        "overperformance_per_90": 0.16,
        "sustainable": false,
        "form": 7.8
    },
    {
        "player": "Wilson",
        "team": "Fulham",
        "team_short": "FUL",
        "goals": 4,
        "xG": 1.6,
        "overperformance": 2.4,
        "overperformance_per_90": 0.16,
        "sustainable": false,
        "form": 7.8
    }
]