[
    {
        "player": "Haaland",
        "team": "Man City",
        "team_short": "MCI",
        "goals": 22,
        "xG": 20.6,
        "overperformance": 1.4,
        "overperformance_per_90": 0.051,
        "sustainable": true,
        "form": 5.0
    },
    {
        "player": "João Pedro",
        "team": "Chelsea",
        "team_short": "CHE",
        "goals": 11,
        "xG": 10.1,
        "overperformance": 0.9,
        "overperformance_per_90": 0.034,
        "sustainable": true,
        "form": 8.5
    },
    {
        "player": "Calvert-Lewin",
        "team": "Leeds",
        "team_short": "LEE",
        "goals": 10,
        "xG": 9.6,
        "overperformance": 0.4,
        "overperformance_per_90": 0.014,
        "sustainable": true,
        "form": 2.3
    },
    {
        "player": "Ekitiké",
        "team": "Liverpool",
        "team_short": "LIV",
        "goals": 10,
        "xG": 9.3,
        "overperformance": 0.7,
        "overperformance_per_90": 0.024,
        "sustainable": true,
        "form": 3.6
    },
    {
        "player": "Welbeck",
        "team": "Brighton",
        "team_short": "BHA",
        "goals": 9,
        "xG": 8.8,
        "overperformance": 0.2,
        "overperformance_per_90": 0.008,
        "sustainable": true,
        "form": 2.9
    },
    {
        "player": "Palmer",
        "team": "Chelsea",
        "team_short": "CHE",
        "goals": 8,
        "xG": 8.1,
        "overperformance": -0.1,
        "overperformance_per_90": -0.003,
        "sustainable": true,
        "form": 6.7
    },
    {
        "player": "Nmecha",
        "team": "Leeds",
        "team_short": "LEE",
        "goals": 6,
        "xG": 6.2,
        "overperformance": -0.2,
        "overperformance_per_90": -0.008,
        "sustainable": true,
        "form": 2.2
    },
    {
        "player": "Barry",
        "team": "Everton",
        "team_short": "EVE",
        "goals": 5,
        "xG": 5.2,
        "overperformance": -0.2,
        "overperformance_per_90": -0.009,
        "sustainable": true,
        "form": 3.1
    }
]