[
    {
        "team": "Arsenal",
        "defense_rank": 1,
        "defense_strength": 0.7092562867843767,
        "overall_strength": 0.89843030465546,
        "players": [
            {
                "web_name": "Gabriel",
                "position_name": "Defender",
                "now_cost": 7.1,
                "clean_sheet_rate": 0.5,
                "xcs_per_game": 0.788,
                "goals_per_game": 0.176,
                "assists_per_game": 0.117,
                "goals_conceded_per_game": 1.231,
                "def_contrib_per_game": 0.0,
                "points_per_game": 7.564,
                "points_per_million": 18.169,
                "consistency_score": 0.711,
                "selected_by_percent": 40.4,
                "team_name_short": "ARS",
                "form": 7.0,
                "defender_score": 1.74
            },
            {
                "web_name": "Saliba",
                "position_name": "Defender",
                "now_cost": 6.0,
                "clean_sheet_rate": 0.5,
                "xcs_per_game": 0.745,
                "goals_per_game": 0.0,
                "assists_per_game": 0.0,
                "goals_conceded_per_game": 1.164,
                "def_contrib_per_game": 0.0,
                "points_per_game": 4.212,
                "points_per_million": 12.667,
                "consistency_score": 0.752,
                "selected_by_percent": 12.9,
                "team_name_short": "ARS",
                "form": 5.1,
                "defender_score": 1.341
            },
            {
                "web_name": "Raya",
                "position_name": "Goalkeeper",
                "now_cost": 5.9,
                "clean_sheet_rate": 0.5,
                "xcs_per_game": 0.56,
                "goals_per_game": 0.0,
                "assists_per_game": 0.0,
                "goals_conceded_per_game": 0.875,
                "def_contrib_per_game": 0.0,
                "points_per_game": 4.125,
                "points_per_million": 16.78,
                "consistency_score": 1.0,
                "selected_by_percent": 33.6,
                "team_name_short": "ARS",
                "form": 4.8,
                "defender_score": 1.317
            },
            {
                "web_name": "J.Timber",
                "position_name": "Defender",
                "now_cost": 6.4,
                "clean_sheet_rate": 0.5,
                "xcs_per_game": 0.634,
                "goals_per_game": 0.094,
                "assists_per_game": 0.141,
                "goals_conceded_per_game": 0.99,
                "def_contrib_per_game": 0.0,
                "points_per_game": 5.422,
                "points_per_million": 17.969,
                "consistency_score": 0.884,
                "selected_by_percent": 28.9,
                "team_name_short": "ARS",
                "form": 4.4,
                "defender_score": 1.243
            }
        ]
    },
    {
        "team": "Man City",
        "defense_rank": 2,
        "defense_strength": 0.5848443465901174,
        "overall_strength": 0.8291463869875213,
        "players": [
            {
                "web_name": "Donnarumma",
                "position_name": "Goalkeeper",
                "now_cost": 5.6,
                "clean_sheet_rate": 0.429,
                "xcs_per_game": 0.302,
                "goals_per_game": 0.0,
                "assists_per_game": 0.0,
                "goals_conceded_per_game": 1.048,
                "def_contrib_per_game": 0.0,
                "points_per_game": 3.857,
                "points_per_million": 14.464,
                "consistency_score": 1.0,
                "selected_by_percent": 8.9,
                "team_name_short": "MCI",
                "form": 3.6,
                "defender_score": 1.008
            },
            {
                "web_name": "Matheus N.",
                "position_name": "Defender",
                "now_cost": 5.4,
                "clean_sheet_rate": 0.417,
                "xcs_per_game": 0.369,
                "goals_per_game": 0.051,
                "assists_per_game": 0.205,
                "goals_conceded_per_game": 1.333,
                "def_contrib_per_game": 0.0,
                "points_per_game": 5.436,
                "points_per_million": 19.63,
                "consistency_score": 0.812,
                "selected_by_percent": 3.2,
                "team_name_short": "MCI",
                "form": 3.3,
                "defender_score": 0.934
            },
            {
                "web_name": "Khusanov",
                "position_name": "Defender",
                "now_cost": 5.4,
                "clean_sheet_rate": 0.417,
                "xcs_per_game": 0.998,
                "goals_per_game": 0.0,
                "assists_per_game": 0.0,
                "goals_conceded_per_game": 3.606,
                "def_contrib_per_game": 0.0,
                "points_per_game": 3.328,
                "points_per_million": 4.444,
                "consistency_score": 0.3,
                "selected_by_percent": 0.4,
                "team_name_short": "MCI",
                "form": 2.6,
                "defender_score": 0.735
            },
            {
                "web_name": "O'Reilly",
                "position_name": "Defender",
                "now_cost": 5.0,
                "clean_sheet_rate": 0.417,
                "xcs_per_game": 0.381,
                "goals_per_game": 0.053,
                "assists_per_game": 0.159,
                "goals_conceded_per_game": 1.376,
                "def_contrib_per_game": 0.0,
                "points_per_game": 4.497,
                "points_per_million": 17.0,
                "consistency_score": 0.788,
                "selected_by_percent": 5.1,
                "team_name_short": "MCI",
                "form": 2.0,
                "defender_score": 0.671
            }
        ]
    },
    {
        "team": "Chelsea",
        "defense_rank": 3,
        "defense_strength": 0.551530612244898,
        "overall_strength": 0.7077728187084074,
        "players": [
            {
                "web_name": "Chalobah",
                "position_name": "Defender",
                "now_cost": 5.7,
                "clean_sheet_rate": 0.375,
                "xcs_per_game": 0.286,
                "goals_per_game": 0.134,
                "assists_per_game": 0.0,
                "goals_conceded_per_game": 1.209,
                "def_contrib_per_game": 0.0,
                "points_per_game": 5.239,
                "points_per_million": 20.526,
                "consistency_score": 0.931,
                "selected_by_percent": 23.6,
                "team_name_short": "CHE",
                "form": 4.8,
                "defender_score": 1.23
            },
            {
                "web_name": "Sánchez",
                "position_name": "Goalkeeper",
                "now_cost": 4.9,
                "clean_sheet_rate": 0.375,
                "xcs_per_game": 0.29,
                "goals_per_game": 0.0,
                "assists_per_game": 0.045,
                "goals_conceded_per_game": 1.225,
                "def_contrib_per_game": 0.0,
                "points_per_game": 4.083,
                "points_per_million": 18.367,
                "consistency_score": 0.919,
                "selected_by_percent": 15.1,
                "team_name_short": "CHE",
                "form": 4.3,
                "defender_score": 1.118
            },
            {
                "web_name": "James",
                "position_name": "Defender",
                "now_cost": 5.7,
                "clean_sheet_rate": 0.375,
                "xcs_per_game": 0.375,
                "goals_per_game": 0.117,
                "assists_per_game": 0.235,
                "goals_conceded_per_game": 1.584,
                "def_contrib_per_game": 0.0,
                "points_per_game": 5.691,
                "points_per_million": 17.018,
                "consistency_score": 0.71,
                "selected_by_percent": 10.9,
                "team_name_short": "CHE",
                "form": 3.5,
                "defender_score": 0.954
            },
            {
                "web_name": "Cucurella",
                "position_name": "Defender",
                "now_cost": 6.0,
                "clean_sheet_rate": 0.375,
                "xcs_per_game": 0.329,
                "goals_per_game": 0.051,
                "assists_per_game": 0.103,
                "goals_conceded_per_game": 1.389,
                "def_contrib_per_game": 0.0,
                "points_per_game": 4.371,
                "points_per_million": 14.167,
                "consistency_score": 0.81,
                "selected_by_percent": 17.0,
                "team_name_short": "CHE",
                "form": 2.9,
                "defender_score": 0.834
            }
        ]
    },
    {
        "team": "Everton",
        "defense_rank": 4,
        "defense_strength": 0.5157894736842105,
        "overall_strength": 0.39706477894005077,
        "players": [
            {
                "web_name": "Pickford",
                "position_name": "Goalkeeper",
                "now_cost": 5.6,
                "clean_sheet_rate": 0.333,
                "xcs_per_game": 0.245,
                "goals_per_game": 0.0,
                "assists_per_game": 0.0,
                "goals_conceded_per_game": 1.167,
                "def_contrib_per_game": 0.0,
                "points_per_game": 4.375,
                "points_per_million": 18.75,
                "consistency_score": 1.0,
                "selected_by_percent": 14.2,
                "team_name_short": "EVE",
                "form": 4.6,
                "defender_score": 1.177
            },
            {
                "web_name": "Tarkowski",
                "position_name": "Defender",
                "now_cost": 5.8,
                "clean_sheet_rate": 0.333,
                "xcs_per_game": 0.245,
                "goals_per_game": 0.0,
                "assists_per_game": 0.042,
                "goals_conceded_per_game": 1.167,
                "def_contrib_per_game": 0.0,
                "points_per_game": 4.75,
                "points_per_million": 19.655,
                "consistency_score": 1.0,
                "selected_by_percent": 13.9,
                "team_name_short": "EVE",
                "form": 4.4,
                "defender_score": 1.143
            },
            {
                "web_name": "O'Brien",
                "position_name": "Defender",
                "now_cost": 4.9,
                "clean_sheet_rate": 0.333,
                "xcs_per_game": 0.261,
                "goals_per_game": 0.0,
                "assists_per_game": 0.044,
                "goals_conceded_per_game": 1.243,
                "def_contrib_per_game": 0.0,
                "points_per_game": 3.772,
                "points_per_million": 17.347,
                "consistency_score": 0.939,
                "selected_by_percent": 0.9,
                "team_name_short": "EVE",
                "form": 4.4,
                "defender_score": 1.132
            },
            {
                "web_name": "Patterson",
                "position_name": "Defender",
                "now_cost": 4.4,
                "clean_sheet_rate": 0.333,
                "xcs_per_game": 2.229,
                "goals_per_game": 0.0,
                "assists_per_game": 0.0,
                "goals_conceded_per_game": 10.633,
                "def_contrib_per_game": 0.0,
                "points_per_game": 7.975,
                "points_per_million": 4.773,
                "consistency_score": 0.11,
                "selected_by_percent": 0.0,
                "team_name_short": "EVE",
                "form": 2.6,
                "defender_score": 0.807
            }
        ]
    },
    {
        "team": "Aston Villa",
        "defense_rank": 5,
        "defense_strength": 0.51151966471106,
        "overall_strength": 0.6012217322012745,
        "players": [
            {
                "web_name": "Cash",
                "position_name": "Defender",
                "now_cost": 4.8,
                "clean_sheet_rate": 0.292,
                "xcs_per_game": 0.265,
                "goals_per_game": 0.132,
                "assists_per_game": 0.088,
                "goals_conceded_per_game": 1.146,
                "def_contrib_per_game": 0.0,
                "points_per_game": 4.277,
                "points_per_million": 20.208,
                "consistency_score": 0.945,
                "selected_by_percent": 11.7,
                "team_name_short": "AVL",
                "form": 4.6,
                "defender_score": 1.189
            },
            {
                "web_name": "Konsa",
                "position_name": "Defender",
                "now_cost": 4.4,
                "clean_sheet_rate": 0.292,
                "xcs_per_game": 0.264,
                "goals_per_game": 0.0,
                "assists_per_game": 0.0,
                "goals_conceded_per_game": 1.144,
                "def_contrib_per_game": 0.0,
                "points_per_game": 3.169,
                "points_per_million": 16.364,
                "consistency_score": 0.947,
                "selected_by_percent": 7.6,
                "team_name_short": "AVL",
                "form": 4.2,
                "defender_score": 1.09
            },
            {
                "web_name": "Martinez",
                "position_name": "Goalkeeper",
                "now_cost": 5.0,
                "clean_sheet_rate": 0.292,
                "xcs_per_game": 0.308,
                "goals_per_game": 0.0,
                "assists_per_game": 0.0,
                "goals_conceded_per_game": 1.333,
                "def_contrib_per_game": 0.0,
                "points_per_game": 4.0,
                "points_per_million": 15.6,
                "consistency_score": 0.812,
                "selected_by_percent": 3.4,
                "team_name_short": "AVL",
                "form": 4.3,
                "defender_score": 1.088
            },
            {
                "web_name": "Digne",
                "position_name": "Defender",
                "now_cost": 4.5,
                "clean_sheet_rate": 0.292,
                "xcs_per_game": 0.442,
                "goals_per_game": 0.0,
                "assists_per_game": 0.294,
                "goals_conceded_per_game": 1.912,
                "def_contrib_per_game": 0.0,
                "points_per_game": 5.0,
                "points_per_million": 15.111,
                "consistency_score": 0.567,
                "selected_by_percent": 1.6,
                "team_name_short": "AVL",
                "form": 3.1,
                "defender_score": 0.839
            }
        ]
    },
    {
        "team": "Newcastle",
        "defense_rank": 6,
        "defense_strength": 0.4874251497005988,
        "overall_strength": 0.43740217408018567,
        "players": [
            {
                "web_name": "Thiaw",
                "position_name": "Defender",
                "now_cost": 5.1,
                "clean_sheet_rate": 0.333,
                "xcs_per_game": 0.429,
                "goals_per_game": 0.154,
                "assists_per_game": 0.0,
                "goals_conceded_per_game": 1.588,
                "def_contrib_per_game": 0.0,
                "points_per_game": 4.354,
                "points_per_million": 16.667,
                "consistency_score": 0.813,
                "selected_by_percent": 5.3,
                "team_name_short": "NEW",
                "form": 5.7,
                "defender_score": 1.398
            },
            {
                "web_name": "Hall",
                "position_name": "Defender",
                "now_cost": 5.3,
                "clean_sheet_rate": 0.333,
                "xcs_per_game": 0.624,
                "goals_per_game": 0.0,
                "assists_per_game": 0.075,
                "goals_conceded_per_game": 2.31,
                "def_contrib_per_game": 0.0,
                "points_per_game": 4.098,
                "points_per_million": 10.377,
                "consistency_score": 0.559,
                "selected_by_percent": 3.0,
                "team_name_short": "NEW",
                "form": 5.1,
                "defender_score": 1.243
            },
            {
                "web_name": "Pope",
                "position_name": "Goalkeeper",
                "now_cost": 5.1,
                "clean_sheet_rate": 0.333,
                "xcs_per_game": 0.47,
                "goals_per_game": 0.0,
                "assists_per_game": 0.0,
                "goals_conceded_per_game": 1.737,
                "def_contrib_per_game": 0.0,
                "points_per_game": 4.203,
                "points_per_million": 14.706,
                "consistency_score": 0.744,
                "selected_by_percent": 4.9,
                "team_name_short": "NEW",
                "form": 4.3,
                "defender_score": 1.093
            },
            {
                "web_name": "Botman",
                "position_name": "Defender",
                "now_cost": 4.9,
                "clean_sheet_rate": 0.333,
                "xcs_per_game": 0.857,
                "goals_per_game": 0.0,
                "assists_per_game": 0.102,
                "goals_conceded_per_game": 3.17,
                "def_contrib_per_game": 0.0,
                "points_per_game": 4.5,
                "points_per_million": 8.98,
                "consistency_score": 0.407,
                "selected_by_percent": 0.4,
                "team_name_short": "NEW",
                "form": 2.6,
                "defender_score": 0.736
            }
        ]
    },
    {
        "team": "Crystal Palace",
        "defense_rank": 7,
        "defense_strength": 0.46908164976449845,
        "overall_strength": 0.40820289496908724,
        "players": [
            {
                "web_name": "Lacroix",
                "position_name": "Defender",
                "now_cost": 5.1,
                "clean_sheet_rate": 0.292,
                "xcs_per_game": 0.262,
                "goals_per_game": 0.0,
                "assists_per_game": 0.083,
                "goals_conceded_per_game": 1.25,
                "def_contrib_per_game": 0.0,
                "points_per_game": 4.25,
                "points_per_million": 20.0,
                "consistency_score": 1.0,
                "selected_by_percent": 5.7,
                "team_name_short": "CRY",
                "form": 3.3,
                "defender_score": 0.92
            },
            {
                "web_name": "Guéhi",
                "position_name": "Defender",
                "now_cost": 5.2,
                "clean_sheet_rate": 0.318,
                "xcs_per_game": 0.284,
                "goals_per_game": 0.1,
                "assists_per_game": 0.1,
                "goals_conceded_per_game": 1.3,
                "def_contrib_per_game": 0.0,
                "points_per_game": 5.25,
                "points_per_million": 20.192,
                "consistency_score": 0.909,
                "selected_by_percent": 36.7,
                "team_name_short": "CRY",
                "form": 2.6,
                "defender_score": 0.783
            },
            {
                "web_name": "Canvot",
                "position_name": "Defender",
                "now_cost": 4.5,
                "clean_sheet_rate": 0.238,
                "xcs_per_game": 1.411,
                "goals_per_game": 0.0,
                "assists_per_game": 0.0,
                "goals_conceded_per_game": 7.415,
                "def_contrib_per_game": 0.0,
                "points_per_game": 6.903,
                "points_per_million": 6.0,
                "consistency_score": 0.186,
                "selected_by_percent": 0.0,
                "team_name_short": "CRY",
                "form": 2.6,
                "defender_score": 0.727
            },
            {
                "web_name": "Mitchell",
                "position_name": "Defender",
                "now_cost": 5.0,
                "clean_sheet_rate": 0.292,
                "xcs_per_game": 0.266,
                "goals_per_game": 0.042,
                "assists_per_game": 0.0,
                "goals_conceded_per_game": 1.269,
                "def_contrib_per_game": 0.0,
                "points_per_game": 3.68,
                "points_per_million": 17.4,
                "consistency_score": 0.985,
                "selected_by_percent": 2.0,
                "team_name_short": "CRY",
                "form": 2.2,
                "defender_score": 0.695
            }
        ]
    },
    {
        "team": "Sunderland",
        "defense_rank": 8,
        "defense_strength": 0.4636849378166743,
        "overall_strength": 0.2707039818923531,
        "players": [
            {
                "web_name": "Mukiele",
                "position_name": "Defender",
                "now_cost": 4.6,
                "clean_sheet_rate": 0.217,
                "xcs_per_game": 0.274,
                "goals_per_game": 0.046,
                "assists_per_game": 0.137,
                "goals_conceded_per_game": 1.278,
                "def_contrib_per_game": 0.0,
                "points_per_game": 5.066,
                "points_per_million": 24.13,
                "consistency_score": 0.953,
                "selected_by_percent": 13.6,
                "team_name_short": "SUN",
                "form": 5.7,
                "defender_score": 1.391
            },
            {
                "web_name": "Ballard",
                "position_name": "Defender",
                "now_cost": 4.6,
                "clean_sheet_rate": 0.25,
                "xcs_per_game": 0.396,
                "goals_per_game": 0.121,
                "assists_per_game": 0.0,
                "goals_conceded_per_game": 1.69,
                "def_contrib_per_game": 0.0,
                "points_per_game": 5.553,
                "points_per_million": 20.0,
                "consistency_score": 0.69,
                "selected_by_percent": 3.1,
                "team_name_short": "SUN",
                "form": 3.7,
                "defender_score": 0.959
            },
            {
                "web_name": "Roefs",
                "position_name": "Goalkeeper",
                "now_cost": 5.0,
                "clean_sheet_rate": 0.25,
                "xcs_per_game": 0.273,
                "goals_per_game": 0.0,
                "assists_per_game": 0.0,
                "goals_conceded_per_game": 1.167,
                "def_contrib_per_game": 0.0,
                "points_per_game": 4.333,
                "points_per_million": 20.8,
                "consistency_score": 1.0,
                "selected_by_percent": 12.5,
                "team_name_short": "SUN",
                "form": 3.4,
                "defender_score": 0.931
            },
            {
                "web_name": "Reinildo",
                "position_name": "Defender",
                "now_cost": 3.8,
                "clean_sheet_rate": 0.25,
                "xcs_per_game": 0.473,
                "goals_per_game": 0.0,
                "assists_per_game": 0.072,
                "goals_conceded_per_game": 2.021,
                "def_contrib_per_game": 0.0,
                "points_per_game": 3.536,
                "points_per_million": 12.895,
                "consistency_score": 0.577,
                "selected_by_percent": 3.0,
                "team_name_short": "SUN",
                "form": 2.6,
                "defender_score": 0.717
            }
        ]
    },
    {
        "team": "Brighton",
        "defense_rank": 9,
        "defense_strength": 0.4462962962962963,
        "overall_strength": 0.5597221695747061,
        "players": [
            {
                "web_name": "Van Hecke",
                "position_name": "Defender",
                "now_cost": 4.5,
                "clean_sheet_rate": 0.25,
                "xcs_per_game": 0.242,
                "goals_per_game": 0.13,
                "assists_per_game": 0.087,
                "goals_conceded_per_game": 1.304,
                "def_contrib_per_game": 0.0,
                "points_per_game": 3.783,
                "points_per_million": 19.333,
                "consistency_score": 0.958,
                "selected_by_percent": 4.4,
                "team_name_short": "BHA",
                "form": 4.0,
                "defender_score": 1.056
            },
            {
                "web_name": "Dunk",
                "position_name": "Defender",
                "now_cost": 4.5,
                "clean_sheet_rate": 0.25,
                "xcs_per_game": 0.248,
                "goals_per_game": 0.0,
                "assists_per_game": 0.0,
                "goals_conceded_per_game": 1.333,
                "def_contrib_per_game": 0.0,
                "points_per_game": 2.533,
                "points_per_million": 12.667,
                "consistency_score": 0.938,
                "selected_by_percent": 1.0,
                "team_name_short": "BHA",
                "form": 4.0,
                "defender_score": 1.034
            },
            {
                "web_name": "Verbruggen",
                "position_name": "Goalkeeper",
                "now_cost": 4.5,
                "clean_sheet_rate": 0.25,
                "xcs_per_game": 0.232,
                "goals_per_game": 0.0,
                "assists_per_game": 0.0,
                "goals_conceded_per_game": 1.25,
                "def_contrib_per_game": 0.0,
                "points_per_game": 3.083,
                "points_per_million": 16.444,
                "consistency_score": 1.0,
                "selected_by_percent": 5.8,
                "team_name_short": "BHA",
                "form": 3.8,
                "defender_score": 1.002
            },
            {
                "web_name": "F.Kadıoğlu",
                "position_name": "Defender",
                "now_cost": 4.4,
                "clean_sheet_rate": 0.25,
                "xcs_per_game": 0.268,
                "goals_per_game": 0.0,
                "assists_per_game": 0.0,
                "goals_conceded_per_game": 1.444,
                "def_contrib_per_game": 0.0,
                "points_per_game": 2.936,
                "points_per_million": 13.864,
                "consistency_score": 0.866,
                "selected_by_percent": 0.4,
                "team_name_short": "BHA",
                "form": 3.5,
                "defender_score": 0.925
            }
        ]
    },
    {
        "team": "Liverpool",
        "defense_rank": 10,
        "defense_strength": 0.43873626373626373,
        "overall_strength": 0.6924857237181804,
        "players": [
            {
                "web_name": "Virgil",
                "position_name": "Defender",
                "now_cost": 5.9,
                "clean_sheet_rate": 0.292,
                "xcs_per_game": 0.363,
                "goals_per_game": 0.042,
                "assists_per_game": 0.0,
                "goals_conceded_per_game": 1.417,
                "def_contrib_per_game": 0.0,
                "points_per_game": 3.917,
                "points_per_million": 15.932,
                "consistency_score": 1.0,
                "selected_by_percent": 21.6,
                "team_name_short": "LIV",
                "form": 4.8,
                "defender_score": 1.228
            },
            {
                "web_name": "Konaté",
                "position_name": "Defender",
                "now_cost": 5.4,
                "clean_sheet_rate": 0.292,
                "xcs_per_game": 0.399,
                "goals_per_game": 0.046,
                "assists_per_game": 0.0,
                "goals_conceded_per_game": 1.556,
                "def_contrib_per_game": 0.0,
                "points_per_game": 4.212,
                "points_per_million": 17.037,
                "consistency_score": 0.91,
                "selected_by_percent": 2.9,
                "team_name_short": "LIV",
                "form": 4.6,
                "defender_score": 1.175
            },
            {
                "web_name": "A.Becker",
                "position_name": "Goalkeeper",
                "now_cost": 5.4,
                "clean_sheet_rate": 0.292,
                "xcs_per_game": 0.458,
                "goals_per_game": 0.0,
                "assists_per_game": 0.0,
                "goals_conceded_per_game": 1.789,
                "def_contrib_per_game": 0.0,
                "points_per_game": 3.526,
                "points_per_million": 12.407,
                "consistency_score": 0.792,
                "selected_by_percent": 5.9,
                "team_name_short": "LIV",
                "form": 3.8,
                "defender_score": 0.994
            },
            {
                "web_name": "Kerkez",
                "position_name": "Defender",
                "now_cost": 5.6,
                "clean_sheet_rate": 0.292,
                "xcs_per_game": 0.482,
                "goals_per_game": 0.055,
                "assists_per_game": 0.055,
                "goals_conceded_per_game": 1.883,
                "def_contrib_per_game": 0.0,
                "points_per_game": 3.212,
                "points_per_million": 10.357,
                "consistency_score": 0.752,
                "selected_by_percent": 2.9,
                "team_name_short": "LIV",
                "form": 3.5,
                "defender_score": 0.939
            }
        ]
    },
    {
        "team": "Brentford",
        "defense_rank": 11,
        "defense_strength": 0.43742514970059876,
        "overall_strength": 0.3770625162335848,
        "players": [
            {
                "web_name": "Kelleher",
                "position_name": "Goalkeeper",
                "now_cost": 4.6,
                "clean_sheet_rate": 0.25,
                "xcs_per_game": 0.242,
                "goals_per_game": 0.0,
                "assists_per_game": 0.0,
                "goals_conceded_per_game": 1.292,
                "def_contrib_per_game": 0.0,
                "points_per_game": 3.875,
                "points_per_million": 20.217,
                "consistency_score": 1.0,
                "selected_by_percent": 10.2,
                "team_name_short": "BRE",
                "form": 6.5,
                "defender_score": 1.543
            },
            {
                "web_name": "Collins",
                "position_name": "Defender",
                "now_cost": 5.0,
                "clean_sheet_rate": 0.25,
                "xcs_per_game": 0.258,
                "goals_per_game": 0.044,
                "assists_per_game": 0.089,
                "goals_conceded_per_game": 1.377,
                "def_contrib_per_game": 0.0,
                "points_per_game": 4.087,
                "points_per_million": 18.4,
                "consistency_score": 0.938,
                "selected_by_percent": 3.7,
                "team_name_short": "BRE",
                "form": 5.7,
                "defender_score": 1.385
            },
            {
                "web_name": "Ajer",
                "position_name": "Defender",
                "now_cost": 4.4,
                "clean_sheet_rate": 0.25,
                "xcs_per_game": 0.44,
                "goals_per_game": 0.0,
                "assists_per_game": 0.076,
                "goals_conceded_per_game": 2.35,
                "def_contrib_per_game": 0.0,
                "points_per_game": 4.17,
                "points_per_million": 12.5,
                "consistency_score": 0.55,
                "selected_by_percent": 0.2,
                "team_name_short": "BRE",
                "form": 4.0,
                "defender_score": 0.988
            },
            {
                "web_name": "Henry",
                "position_name": "Defender",
                "now_cost": 4.3,
                "clean_sheet_rate": 0.25,
                "xcs_per_game": 0.554,
                "goals_per_game": 0.0,
                "assists_per_game": 0.0,
                "goals_conceded_per_game": 2.962,
                "def_contrib_per_game": 0.0,
                "points_per_game": 4.108,
                "points_per_million": 10.0,
                "consistency_score": 0.436,
                "selected_by_percent": 0.2,
                "team_name_short": "BRE",
                "form": 3.5,
                "defender_score": 0.871
            }
        ]
    },
    {
        "team": "Spurs",
        "defense_rank": 12,
        "defense_strength": 0.4367948077293385,
        "overall_strength": 0.43754226214196346,
        "players": [
            {
                "web_name": "Romero",
                "position_name": "Defender",
                "now_cost": 5.0,
                "clean_sheet_rate": 0.292,
                "xcs_per_game": 0.349,
                "goals_per_game": 0.214,
                "assists_per_game": 0.054,
                "goals_conceded_per_game": 1.819,
                "def_contrib_per_game": 0.0,
                "points_per_game": 4.923,
                "points_per_million": 18.4,
                "consistency_score": 0.779,
                "selected_by_percent": 4.2,
                "team_name_short": "TOT",
                "form": 5.3,
                "defender_score": 1.299
            },
            {
                "web_name": "Van de Ven",
                "position_name": "Defender",
                "now_cost": 4.5,
                "clean_sheet_rate": 0.292,
                "xcs_per_game": 0.298,
                "goals_per_game": 0.183,
                "assists_per_game": 0.046,
                "goals_conceded_per_game": 1.554,
                "def_contrib_per_game": 0.0,
                "points_per_game": 4.388,
                "points_per_million": 21.333,
                "consistency_score": 0.912,
                "selected_by_percent": 24.7,
                "team_name_short": "TOT",
                "form": 3.1,
                "defender_score": 0.874
            },
            {
                "web_name": "Pedro Porro",
                "position_name": "Defender",
                "now_cost": 5.2,
                "clean_sheet_rate": 0.292,
                "xcs_per_game": 0.322,
                "goals_per_game": 0.0,
                "assists_per_game": 0.099,
                "goals_conceded_per_game": 1.681,
                "def_contrib_per_game": 0.0,
                "points_per_game": 3.907,
                "points_per_million": 15.192,
                "consistency_score": 0.843,
                "selected_by_percent": 10.6,
                "team_name_short": "TOT",
                "form": 2.0,
                "defender_score": 0.634
            },
            {
                "web_name": "Vicario",
                "position_name": "Goalkeeper",
                "now_cost": 4.8,
                "clean_sheet_rate": 0.292,
                "xcs_per_game": 0.272,
                "goals_per_game": 0.0,
                "assists_per_game": 0.0,
                "goals_conceded_per_game": 1.417,
                "def_contrib_per_game": 0.0,
                "points_per_game": 3.25,
                "points_per_million": 16.25,
                "consistency_score": 1.0,
                "selected_by_percent": 6.2,
                "team_name_short": "TOT",
                "form": 1.4,
                "defender_score": 0.526
            }
        ]
    },
    {
        "team": "Nott'm Forest",
        "defense_rank": 13,
        "defense_strength": 0.41810834874323677,
        "overall_strength": 0.3650487704125994,
        "players": [
            {
                "web_name": "Murillo",
                "position_name": "Defender",
                "now_cost": 5.2,
                "clean_sheet_rate": 0.25,
                "xcs_per_game": 0.296,
                "goals_per_game": 0.058,
                "assists_per_game": 0.0,
                "goals_conceded_per_game": 1.917,
                "def_contrib_per_game": 0.0,
                "points_per_game": 3.719,
                "points_per_million": 12.308,
                "consistency_score": 0.717,
                "selected_by_percent": 2.2,
                "team_name_short": "NFO",
                "form": 5.1,
                "defender_score": 1.219
            },
            {
                "web_name": "Sels",
                "position_name": "Goalkeeper",
                "now_cost": 4.6,
                "clean_sheet_rate": 0.25,
                "xcs_per_game": 0.274,
                "goals_per_game": 0.0,
                "assists_per_game": 0.0,
                "goals_conceded_per_game": 1.771,
                "def_contrib_per_game": 0.0,
                "points_per_game": 3.274,
                "points_per_million": 13.261,
                "consistency_score": 0.776,
                "selected_by_percent": 5.6,
                "team_name_short": "NFO",
                "form": 5.0,
                "defender_score": 1.201
            },
            {
                "web_name": "Milenković",
                "position_name": "Defender",
                "now_cost": 5.1,
                "clean_sheet_rate": 0.25,
                "xcs_per_game": 0.212,
                "goals_per_game": 0.0,
                "assists_per_game": 0.0,
                "goals_conceded_per_game": 1.375,
                "def_contrib_per_game": 0.0,
                "points_per_game": 2.875,
                "points_per_million": 13.529,
                "consistency_score": 1.0,
                "selected_by_percent": 3.2,
                "team_name_short": "NFO",
                "form": 4.8,
                "defender_score": 1.196
            },
            {
                "web_name": "Aina",
                "position_name": "Defender",
                "now_cost": 4.7,
                "clean_sheet_rate": 0.25,
                "xcs_per_game": 0.658,
                "goals_per_game": 0.0,
                "assists_per_game": 0.0,
                "goals_conceded_per_game": 4.255,
                "def_contrib_per_game": 0.0,
                "points_per_game": 3.481,
                "points_per_million": 5.745,
                "consistency_score": 0.323,
                "selected_by_percent": 2.2,
                "team_name_short": "NFO",
                "form": 4.6,
                "defender_score": 1.079
            }
        ]
    },
    {
        "team": "Bournemouth",
        "defense_rank": 14,
        "defense_strength": 0.364812030075188,
        "overall_strength": 0.5620967155904921,
        "players": [
            {
                "web_name": "Senesi",
                "position_name": "Defender",
                "now_cost": 4.8,
                "clean_sheet_rate": 0.25,
                "xcs_per_game": 0.332,
                "goals_per_game": 0.0,
                "assists_per_game": 0.178,
                "goals_conceded_per_game": 1.864,
                "def_contrib_per_game": 0.0,
                "points_per_game": 4.527,
                "points_per_million": 21.25,
                "consistency_score": 0.939,
                "selected_by_percent": 15.3,
                "team_name_short": "BOU",
                "form": 4.6,
                "defender_score": 1.164
            },
            {
                "web_name": "Hill",
                "position_name": "Defender",
                "now_cost": 3.9,
                "clean_sheet_rate": 0.25,
                "xcs_per_game": 0.8,
                "goals_per_game": 0.0,
                "assists_per_game": 0.107,
                "goals_conceded_per_game": 4.489,
                "def_contrib_per_game": 0.0,
                "points_per_game": 4.596,
                "points_per_million": 11.026,
                "consistency_score": 0.39,
                "selected_by_percent": 1.4,
                "team_name_short": "BOU",
                "form": 4.6,
                "defender_score": 1.109
            },
            {
                "web_name": "Petrović",
                "position_name": "Goalkeeper",
                "now_cost": 4.5,
                "clean_sheet_rate": 0.25,
                "xcs_per_game": 0.312,
                "goals_per_game": 0.0,
                "assists_per_game": 0.0,
                "goals_conceded_per_game": 1.75,
                "def_contrib_per_game": 0.0,
                "points_per_game": 2.917,
                "points_per_million": 15.556,
                "consistency_score": 1.0,
                "selected_by_percent": 4.3,
                "team_name_short": "BOU",
                "form": 3.6,
                "defender_score": 0.955
            },
            {
                "web_name": "Truffert",
                "position_name": "Defender",
                "now_cost": 4.5,
                "clean_sheet_rate": 0.25,
                "xcs_per_game": 0.318,
                "goals_per_game": 0.0,
                "assists_per_game": 0.042,
                "goals_conceded_per_game": 1.785,
                "def_contrib_per_game": 0.0,
                "points_per_game": 3.399,
                "points_per_million": 17.778,
                "consistency_score": 0.981,
                "selected_by_percent": 1.7,
                "team_name_short": "BOU",
                "form": 3.3,
                "defender_score": 0.897
            }
        ]
    },
    {
        "team": "Fulham",
        "defense_rank": 15,
        "defense_strength": 0.35,
        "overall_strength": 0.3621838607915933,
        "players": [
            {
                "web_name": "Andersen",
                "position_name": "Defender",
                "now_cost": 4.6,
                "clean_sheet_rate": 0.167,
                "xcs_per_game": 0.263,
                "goals_per_game": 0.0,
                "assists_per_game": 0.045,
                "goals_conceded_per_game": 1.603,
                "def_contrib_per_game": 0.0,
                "points_per_game": 3.83,
                "points_per_million": 18.696,
                "consistency_score": 0.936,
                "selected_by_percent": 5.2,
                "team_name_short": "FUL",
                "form": 3.3,
                "defender_score": 0.881
            },
            {
                "web_name": "Leno",
                "position_name": "Goalkeeper",
                "now_cost": 4.9,
                "clean_sheet_rate": 0.167,
                "xcs_per_game": 0.246,
                "goals_per_game": 0.0,
                "assists_per_game": 0.0,
                "goals_conceded_per_game": 1.5,
                "def_contrib_per_game": 0.0,
                "points_per_game": 3.0,
                "points_per_million": 14.694,
                "consistency_score": 1.0,
                "selected_by_percent": 1.6,
                "team_name_short": "FUL",
                "form": 2.9,
                "defender_score": 0.804
            },
            {
                "web_name": "J.Cuenca",
                "position_name": "Defender",
                "now_cost": 4.3,
                "clean_sheet_rate": 0.167,
                "xcs_per_game": 0.635,
                "goals_per_game": 0.0,
                "assists_per_game": 0.0,
                "goals_conceded_per_game": 3.866,
                "def_contrib_per_game": 0.0,
                "points_per_game": 3.759,
                "points_per_million": 8.14,
                "consistency_score": 0.388,
                "selected_by_percent": 0.1,
                "team_name_short": "FUL",
                "form": 2.4,
                "defender_score": 0.636
            },
            {
                "web_name": "Castagne",
                "position_name": "Defender",
                "now_cost": 4.3,
                "clean_sheet_rate": 0.167,
                "xcs_per_game": 0.514,
                "goals_per_game": 0.0,
                "assists_per_game": 0.0,
                "goals_conceded_per_game": 3.133,
                "def_contrib_per_game": 0.0,
                "points_per_game": 2.263,
                "points_per_million": 6.047,
                "consistency_score": 0.479,
                "selected_by_percent": 0.1,
                "team_name_short": "FUL",
                "form": 1.8,
                "defender_score": 0.522
            }
        ]
    },
    {
        "team": "Leeds",
        "defense_rank": 16,
        "defense_strength": 0.3455063906613821,
        "overall_strength": 0.32705616067380944,
        "players": [
            {
                "web_name": "Struijk",
                "position_name": "Defender",
                "now_cost": 4.3,
                "clean_sheet_rate": 0.208,
                "xcs_per_game": 0.316,
                "goals_per_game": 0.0,
                "assists_per_game": 0.047,
                "goals_conceded_per_game": 1.944,
                "def_contrib_per_game": 0.0,
                "points_per_game": 3.319,
                "points_per_million": 16.279,
                "consistency_score": 0.879,
                "selected_by_percent": 0.5,
                "team_name_short": "LEE",
                "form": 4.8,
                "defender_score": 1.178
            },
            {
                "web_name": "Justin",
                "position_name": "Defender",
                "now_cost": 3.9,
                "clean_sheet_rate": 0.182,
                "xcs_per_game": 0.86,
                "goals_per_game": 0.138,
                "assists_per_game": 0.0,
                "goals_conceded_per_game": 4.954,
                "def_contrib_per_game": 0.0,
                "points_per_game": 4.954,
                "points_per_million": 9.231,
                "consistency_score": 0.33,
                "selected_by_percent": 0.6,
                "team_name_short": "LEE",
                "form": 4.8,
                "defender_score": 1.142
            },
            {
                "web_name": "Rodon",
                "position_name": "Defender",
                "now_cost": 3.9,
                "clean_sheet_rate": 0.208,
                "xcs_per_game": 0.312,
                "goals_per_game": 0.094,
                "assists_per_game": 0.0,
                "goals_conceded_per_game": 1.922,
                "def_contrib_per_game": 0.0,
                "points_per_game": 3.281,
                "points_per_million": 17.949,
                "consistency_score": 0.889,
                "selected_by_percent": 3.6,
                "team_name_short": "LEE",
                "form": 2.9,
                "defender_score": 0.801
            },
            {
                "web_name": "Bornauw",
                "position_name": "Defender",
                "now_cost": 3.8,
                "clean_sheet_rate": 0.208,
                "xcs_per_game": 2.407,
                "goals_per_game": 0.0,
                "assists_per_game": 0.0,
                "goals_conceded_per_game": 14.819,
                "def_contrib_per_game": 0.0,
                "points_per_game": 5.783,
                "points_per_million": 4.211,
                "consistency_score": 0.115,
                "selected_by_percent": 0.1,
                "team_name_short": "LEE",
                "form": 1.8,
                "defender_score": 0.647
            }
        ]
    },
    {
        "team": "Man Utd",
        "defense_rank": 17,
        "defense_strength": 0.3233464769415395,
        "overall_strength": 0.693939759679773,
        "players": [
            {
                "web_name": "Dorgu",
                "position_name": "Defender",
                "now_cost": 4.4,
                "clean_sheet_rate": 0.125,
                "xcs_per_game": 0.461,
                "goals_per_game": 0.203,
                "assists_per_game": 0.203,
                "goals_conceded_per_game": 2.438,
                "def_contrib_per_game": 0.0,
                "points_per_game": 5.011,
                "points_per_million": 16.818,
                "consistency_score": 0.615,
                "selected_by_percent": 6.5,
                "team_name_short": "MUN",
                "form": 6.4,
                "defender_score": 1.492
            },
            {
                "web_name": "Lammens",
                "position_name": "Goalkeeper",
                "now_cost": 5.0,
                "clean_sheet_rate": 0.143,
                "xcs_per_game": 0.358,
                "goals_per_game": 0.0,
                "assists_per_game": 0.0,
                "goals_conceded_per_game": 1.667,
                "def_contrib_per_game": 0.0,
                "points_per_game": 2.833,
                "points_per_million": 10.2,
                "consistency_score": 0.857,
                "selected_by_percent": 1.9,
                "team_name_short": "MUN",
                "form": 3.1,
                "defender_score": 0.833
            },
            {
                "web_name": "Dalot",
                "position_name": "Defender",
                "now_cost": 4.5,
                "clean_sheet_rate": 0.125,
                "xcs_per_game": 0.367,
                "goals_per_game": 0.054,
                "assists_per_game": 0.108,
                "goals_conceded_per_game": 1.941,
                "def_contrib_per_game": 0.0,
                "points_per_game": 3.936,
                "points_per_million": 16.222,
                "consistency_score": 0.773,
                "selected_by_percent": 3.6,
                "team_name_short": "MUN",
                "form": 2.4,
                "defender_score": 0.691
            },
            {
                "web_name": "Maguire",
                "position_name": "Defender",
                "now_cost": 4.3,
                "clean_sheet_rate": 0.125,
                "xcs_per_game": 1.003,
                "goals_per_game": 0.147,
                "assists_per_game": 0.147,
                "goals_conceded_per_game": 5.303,
                "def_contrib_per_game": 0.0,
                "points_per_game": 6.481,
                "points_per_million": 10.233,
                "consistency_score": 0.283,
                "selected_by_percent": 1.3,
                "team_name_short": "MUN",
                "form": 2.4,
                "defender_score": 0.674
            }
        ]
    },
    {
        "team": "Wolves",
        "defense_rank": 18,
        "defense_strength": 0.2900648596447727,
        "overall_strength": 0.0752709220268494,
        "players": [
            {
                "web_name": "H.Bueno",
                "position_name": "Defender",
                "now_cost": 4.3,
                "clean_sheet_rate": 0.125,
                "xcs_per_game": 0.43,
                "goals_per_game": 0.0,
                "assists_per_game": 0.063,
                "goals_conceded_per_game": 2.651,
                "def_contrib_per_game": 0.0,
                "points_per_game": 3.282,
                "points_per_million": 12.093,
                "consistency_score": 0.66,
                "selected_by_percent": 0.1,
                "team_name_short": "WOL",
                "form": 4.8,
                "defender_score": 1.143
            },
            {
                "web_name": "S.Bueno",
                "position_name": "Defender",
                "now_cost": 4.4,
                "clean_sheet_rate": 0.125,
                "xcs_per_game": 0.474,
                "goals_per_game": 0.139,
                "assists_per_game": 0.0,
                "goals_conceded_per_game": 2.926,
                "def_contrib_per_game": 0.0,
                "points_per_game": 3.622,
                "points_per_million": 11.818,
                "consistency_score": 0.598,
                "selected_by_percent": 0.1,
                "team_name_short": "WOL",
                "form": 3.7,
                "defender_score": 0.924
            },
            {
                "web_name": "José Sá",
                "position_name": "Goalkeeper",
                "now_cost": 4.2,
                "clean_sheet_rate": 0.125,
                "xcs_per_game": 0.568,
                "goals_per_game": 0.0,
                "assists_per_game": 0.0,
                "goals_conceded_per_game": 3.5,
                "def_contrib_per_game": 0.0,
                "points_per_game": 2.333,
                "points_per_million": 6.667,
                "consistency_score": 0.5,
                "selected_by_percent": 1.1,
                "team_name_short": "WOL",
                "form": 3.8,
                "defender_score": 0.921
            },
            {
                "web_name": "Mosquera",
                "position_name": "Defender",
                "now_cost": 4.3,
                "clean_sheet_rate": 0.125,
                "xcs_per_game": 0.54,
                "goals_per_game": 0.0,
                "assists_per_game": 0.0,
                "goals_conceded_per_game": 3.327,
                "def_contrib_per_game": 0.0,
                "points_per_game": 2.06,
                "points_per_million": 6.047,
                "consistency_score": 0.526,
                "selected_by_percent": 0.1,
                "team_name_short": "WOL",
                "form": 3.7,
                "defender_score": 0.906
            }
        ]
    },
    {
        "team": "Burnley",
        "defense_rank": 19,
        "defense_strength": 0.28189655172413797,
        "overall_strength": 0.061066342757669194,
        "players": [
            {
                "web_name": "Dúbravka",
                "position_name": "Goalkeeper",
                "now_cost": 4.0,
                "clean_sheet_rate": 0.125,
                "xcs_per_game": 0.135,
                "goals_per_game": 0.0,
                "assists_per_game": 0.0,
                "goals_conceded_per_game": 1.833,
                "def_contrib_per_game": 0.0,
                "points_per_game": 3.083,
                "points_per_million": 18.5,
                "consistency_score": 1.0,
                "selected_by_percent": 32.9,
                "team_name_short": "BUR",
                "form": 3.6,
                "defender_score": 0.911
            },
            {
                "web_name": "Humphreys",
                "position_name": "Defender",
                "now_cost": 3.9,
                "clean_sheet_rate": 0.125,
                "xcs_per_game": 0.471,
                "goals_per_game": 0.0,
                "assists_per_game": 0.0,
                "goals_conceded_per_game": 6.418,
                "def_contrib_per_game": 0.0,
                "points_per_game": 3.793,
                "points_per_million": 6.667,
                "consistency_score": 0.286,
                "selected_by_percent": 0.1,
                "team_name_short": "BUR",
                "form": 3.5,
                "defender_score": 0.811
            },
            {
                "web_name": "Estève",
                "position_name": "Defender",
                "now_cost": 3.9,
                "clean_sheet_rate": 0.125,
                "xcs_per_game": 0.162,
                "goals_per_game": 0.0,
                "assists_per_game": 0.0,
                "goals_conceded_per_game": 2.214,
                "def_contrib_per_game": 0.0,
                "points_per_game": 2.666,
                "points_per_million": 13.59,
                "consistency_score": 0.828,
                "selected_by_percent": 8.1,
                "team_name_short": "BUR",
                "form": 2.4,
                "defender_score": 0.648
            },
            {
                "web_name": "Tuanzebe",
                "position_name": "Defender",
                "now_cost": 3.9,
                "clean_sheet_rate": 0.125,
                "xcs_per_game": 0.312,
                "goals_per_game": 0.097,
                "assists_per_game": 0.0,
                "goals_conceded_per_game": 4.253,
                "def_contrib_per_game": 0.0,
                "points_per_game": 2.61,
                "points_per_million": 6.923,
                "consistency_score": 0.431,
                "selected_by_percent": 1.0,
                "team_name_short": "BUR",
                "form": 2.0,
                "defender_score": 0.527
            }
        ]
    },
    {
        "team": "West Ham",
        "defense_rank": 20,
        "defense_strength": 0.2048983088398198,
        "overall_strength": 0.12050482674404389,
        "players": [
            {
                "web_name": "Wan-Bissaka",
                "position_name": "Defender",
                "now_cost": 4.1,
                "clean_sheet_rate": 0.042,
                "xcs_per_game": 0.339,
                "goals_per_game": 0.0,
                "assists_per_game": 0.141,
                "goals_conceded_per_game": 3.443,
                "def_contrib_per_game": 0.0,
                "points_per_game": 2.67,
                "points_per_million": 9.268,
                "consistency_score": 0.593,
                "selected_by_percent": 4.2,
                "team_name_short": "WHU",
                "form": 2.9,
                "defender_score": 0.727
            },
            {
                "web_name": "Areola",
                "position_name": "Goalkeeper",
                "now_cost": 4.3,
                "clean_sheet_rate": 0.042,
                "xcs_per_game": 0.242,
                "goals_per_game": 0.0,
                "assists_per_game": 0.05,
                "goals_conceded_per_game": 2.45,
                "def_contrib_per_game": 0.0,
                "points_per_game": 2.55,
                "points_per_million": 11.86,
                "consistency_score": 0.833,
                "selected_by_percent": 2.2,
                "team_name_short": "WHU",
                "form": 2.6,
                "defender_score": 0.688
            },
            {
                "web_name": "Mavropanos",
                "position_name": "Defender",
                "now_cost": 4.4,
                "clean_sheet_rate": 0.042,
                "xcs_per_game": 0.319,
                "goals_per_game": 0.0,
                "assists_per_game": 0.0,
                "goals_conceded_per_game": 3.24,
                "def_contrib_per_game": 0.0,
                "points_per_game": 2.843,
                "points_per_million": 9.773,
                "consistency_score": 0.63,
                "selected_by_percent": 0.1,
                "team_name_short": "WHU",
                "form": 2.6,
                "defender_score": 0.663
            },
            {
                "web_name": "Scarles",
                "position_name": "Defender",
                "now_cost": 4.3,
                "clean_sheet_rate": 0.042,
                "xcs_per_game": 0.687,
                "goals_per_game": 0.0,
                "assists_per_game": 0.0,
                "goals_conceded_per_game": 6.967,
                "def_contrib_per_game": 0.0,
                "points_per_game": 2.701,
                "points_per_million": 4.419,
                "consistency_score": 0.293,
                "selected_by_percent": 0.0,
                "team_name_short": "WHU",
                "form": 2.6,
                "defender_score": 0.644
            }
        ]
    }
]