[
    {
        "player": "Gyökeres",
        "team": "Arsenal",
        "team_short": "ARS",
        "goals": 3,
        "xG": 3.0,
        "overperformance": 0.0,
        "overperformance_per_90": 0.0,
        "sustainable": true,
        "form": 1.8
    },
    {
        "player": "Sarr",
        "team": "Crystal Palace",
        "team_short": "CRY",
        "goals": 3,
        "xG": 2.9,
        "overperformance": 0.1,
        "overperformance_per_90": 0.014,
        "sustainable": true,
        "form": 5.4
    },
    {
        "player": "M.Salah",
        "team": "Liverpool",
        "team_short": "LIV",
        "goals": 2,
        "xG": 2.0,
        "overperformance": 0.0,
        "overperformance_per_90": 0.0,
        "sustainable": true,
        "form": 2.7
    },
    {
        "player": "Casemiro",
        "team": "Man Utd",
        "team_short": "MUN",
        "goals": 1,
        "xG": 1.0,
        "overperformance": 0.0,
        "overperformance_per_90": 0.0,
        "sustainable": true,
        "form": 2.1
    },
    {
        "player": "Calvert-Lewin",
        "team": "Leeds",
        "team_short": "LEE",
        "goals": 1,
        "xG": 1.1,
        "overperformance": -0.1,
        "overperformance_per_90": -0.017,
        "sustainable": true,
        "form": 4.5
    },
    {
        "player": "Reijnders",
        "team": "Man City",
        "team_short": "MCI",
        "goals": 1,
        "xG": 1.0,
        "overperformance": 0.0,
        "overperformance_per_90": 0.0,
        "sustainable": true,
        "form": 4.2
    },
    {
        "player": "Szoboszlai",
        "team": "Liverpool",
        "team_short": "LIV",
        "goals": 1,
        "xG": 1.1,
        "overperformance": -0.1,
        "overperformance_per_90": -0.014,
        "sustainable": true,
        "form": 2.1
    }
]