[
  {
    "player": "Haaland",
    "team": "Man City",
    "team_short": "MCI",
    "position": "Forward",
    "points": 182,
    "ppg": 7.3,
    "price": 14.9,
    "ownership": 68.8,
    "form": 4.5
  },
  {
    "player": "B.Fernandes",
    "team": "Man Utd",
    "team_short": "MUN",
    "position": "Midfielder",
    "points": 143,
    "ppg": 5.5,
    "price": 9.8,
    "ownership": 36.4,
    "form": 6.7
  },
  {
    "player": "Gabriel",
    "team": "Arsenal",
    "team_short": "ARS",
    "position": "Defender",
    "points": 135,
    "ppg": 5.4,
    "price": 7.1,
    "ownership": 42.9,
    "form": 6.4
  },
  {
    "player": "Bruno G.",
    "team": "Newcastle",
    "team_short": "NEW",
    "position": "Midfielder",
    "points": 134,
    "ppg": 5.2,
    "price": 7.0,
    "ownership": 12.6,
    "form": 3.1
  },
  {
    "player": "Rice",
    "team": "Arsenal",
    "team_short": "ARS",
    "position": "Midfielder",
    "points": 134,
    "ppg": 5.4,
    "price": 7.6,
    "ownership": 35.7,
    "form": 2.7
  },
  {
    "player": "João Pedro",
    "team": "Chelsea",
    "team_short": "CHE",
    "position": "Forward",
    "points": 132,
    "ppg": 5.1,
    "price": 7.6,
    "ownership": 44.6,
    "form": 8.6
  },
  {
    "player": "Thiago",
    "team": "Brentford",
    "team_short": "BRE",
    "position": "Forward",
    "points": 131,
    "ppg": 5.2,
    "price": 7.0,
    "ownership": 30.0,
    "form": 4.1
  },
  {
    "player": "Rogers",
    "team": "Aston Villa",
    "team_short": "AVL",
    "position": "Midfielder",
    "points": 123,
    "ppg": 4.9,
    "price": 7.6,
    "ownership": 30.5,
    "form": 4.5
  },
  {
    "player": "Chalobah",
    "team": "Chelsea",
    "team_short": "CHE",
    "position": "Defender",
    "points": 122,
    "ppg": 4.7,
    "price": 5.8,
    "ownership": 23.8,
    "form": 4.4
  },
  {
    "player": "J.Timber",
    "team": "Arsenal",
    "team_short": "ARS",
    "position": "Defender",
    "points": 121,
    "ppg": 4.8,
    "price": 6.4,
    "ownership": 31.2,
    "form": 5.1
  },
  {
    "player": "Bowen",
    "team": "West Ham",
    "team_short": "WHU",
    "position": "Forward",
    "points": 120,
    "ppg": 4.6,
    "price": 7.6,
    "ownership": 8.6,
    "form": 5.4
  },
  {
    "player": "Semenyo",
    "team": "Bournemouth",
    "team_short": "BOU",
    "position": "Midfielder",
    "points": 120,
    "ppg": 5.7,
    "price": 7.9,
    "ownership": 48.7,
    "form": 5.6
  },
  {
    "player": "Enzo",
    "team": "Chelsea",
    "team_short": "CHE",
    "position": "Midfielder",
    "points": 118,
    "ppg": 4.5,
    "price": 6.9,
    "ownership": 23.1,
    "form": 4.7
  },
  {
    "player": "Tarkowski",
    "team": "Everton",
    "team_short": "EVE",
    "position": "Defender",
    "points": 117,
    "ppg": 4.5,
    "price": 5.7,
    "ownership": 12.5,
    "form": 3.7
  },
  {
    "player": "Lacroix",
    "team": "Crystal Palace",
    "team_short": "CRY",
    "position": "Defender",
    "points": 113,
    "ppg": 4.5,
    "price": 5.1,
    "ownership": 6.3,
    "form": 5.1
  }
]