[
  {
    "player": "Haaland",
    "team": "Man City",
    "team_short": "MCI",
    "position": "Forward",
    "points": 104,
    "ppg": 8.7,
    "price": 14.9,
    "ownership": 71.4,
    "form": 5.7
  },
  {
    "player": "Gabriel",
    "team": "Arsenal",
    "team_short": "ARS",
    "position": "Defender",
    "points": 81,
    "ppg": 6.8,
    "price": 6.4,
    "ownership": 28.0,
    "form": 4.8
  },
  {
    "player": "Semenyo",
    "team": "Bournemouth",
    "team_short": "BOU",
    "position": "Midfielder",
    "points": 75,
    "ppg": 6.2,
    "price": 8.0,
    "ownership": 58.0,
    "form": 0.6
  },
  {
    "player": "Muñoz",
    "team": "Crystal Palace",
    "team_short": "CRY",
    "position": "Defender",
    "points": 74,
    "ppg": 6.2,
    "price": 5.9,
    "ownership": 19.4,
    "form": 9.5
  },
  {
    "player": "J.Timber",
    "team": "Arsenal",
    "team_short": "ARS",
    "position": "Defender",
    "points": 72,
    "ppg": 6.0,
    "price": 6.3,
    "ownership": 30.0,
    "form": 4.4
  },
  {
    "player": "Rice",
    "team": "Arsenal",
    "team_short": "ARS",
    "position": "Midfielder",
    "points": 71,
    "ppg": 5.9,
    "price": 6.9,
    "ownership": 22.0,
    "form": 6.3
  },
  {
    "player": "Guéhi",
    "team": "Crystal Palace",
    "team_short": "CRY",
    "position": "Defender",
    "points": 69,
    "ppg": 5.8,
    "price": 5.1,
    "ownership": 34.8,
    "form": 5.5
  },
  {
    "player": "Lacroix",
    "team": "Crystal Palace",
    "team_short": "CRY",
    "position": "Defender",
    "points": 67,
    "ppg": 5.6,
    "price": 5.0,
    "ownership": 4.5,
    "form": 9.2
  },
  {
    "player": "Thiago",
    "team": "Brentford",
    "team_short": "BRE",
    "position": "Forward",
    "points": 64,
    "ppg": 5.3,
    "price": 6.5,
    "ownership": 15.3,
    "form": 5.7
  },
  {
    "player": "Calafiori",
    "team": "Arsenal",
    "team_short": "ARS",
    "position": "Defender",
    "points": 63,
    "ppg": 5.2,
    "price": 5.8,
    "ownership": 14.6,
    "form": 3.3
  },
  {
    "player": "Chalobah",
    "team": "Chelsea",
    "team_short": "CHE",
    "position": "Defender",
    "points": 61,
    "ppg": 5.1,
    "price": 5.1,
    "ownership": 8.6,
    "form": 7.0
  },
  {
    "player": "Minteh",
    "team": "Brighton",
    "team_short": "BHA",
    "position": "Midfielder",
    "points": 61,
    "ppg": 5.1,
    "price": 6.1,
    "ownership": 6.1,
    "form": 6.9
  },
  {
    "player": "Mitchell",
    "team": "Crystal Palace",
    "team_short": "CRY",
    "position": "Defender",
    "points": 61,
    "ppg": 5.1,
    "price": 5.0,
    "ownership": 2.6,
    "form": 8.4
  },
  {
    "player": "Senesi",
    "team": "Bournemouth",
    "team_short": "BOU",
    "position": "Defender",
    "points": 61,
    "ppg": 5.1,
    "price": 5.0,
    "ownership": 26.9,
    "form": 2.9
  },
  {
    "player": "Bruno G.",
    "team": "Newcastle",
    "team_short": "NEW",
    "position": "Midfielder",
    "points": 60,
    "ppg": 5.0,
    "price": 6.6,
    "ownership": 3.7,
    "form": 5.4
  }
]